{
  "project_info": {
    "project_number": "31609493041",
    "firebase_url": "https://tactical-command-center-default-rtdb.firebaseio.com",
    "project_id": "tactical-command-center",
    "storage_bucket": "tactical-command-center.firebasestorage.app"
  },
  "client": [
    {
      "client_info": {
        "mobilesdk_app_id": "1:31609493041:android:fdb77d8e71ab09462f2710",
        "android_client_info": {
          "package_name": "com.tacops.commandcenter"
        }
      },
      "oauth_client": [],
      "api_key": [
        {
          "current_key": "AIzaSyDN2iMTnrHl4P716v2bEz0FDp9oLVY5Hkc"
        }
      ],
      "services": {
        "appinvite_service": {
          "other_platform_oauth_client": []
        }
      }
    }
  ],
  "configuration_version": "1"
}